{
 "result": {
  "imageWidth": 800,
  "imageHeight": 341.57293701171875,
  "interfaceWidth": 805,
  "interfaceHeight": 347,
  "views": {
   "1": {
    "hierarchy": "1",
    "cX": 0.11428571428569875,
    "cY": 0.4697406340057666,
    "cWidth": 0.2285714285713975,
    "cHeight": 0.9394812680115332,
    "viewType": [
     {
      "layout": "Free",
      "Type": "Text Based",
      "probability": "1"
     }
    ],
    "mid_view": {}
   },
   "2": {
    "hierarchy": "2",
    "cX": 0.6043478260868975,
    "cY": 0.328530259366,
    "cWidth": 0.7515527950309999,
    "cHeight": 0.657060518732,
    "viewType": [
     {
      "layout": "Free",
      "Type": "Diagram",
      "probability": "1"
     }
    ],
    "mid_view": {}
   },
   "3": {
    "hierarchy": "3",
    "cX": 0.6043478260868975,
    "cY": 0.7982708933717666,
    "cWidth": 0.7515527950309999,
    "cHeight": 0.28242074927953315,
    "viewType": [
     {
      "Type": "Table",
      "probability": "1"
     }
    ],
    "mid_view": {}
   }
  },
  "tile": 4,
  "interfaceX": 5.0000000000475,
  "interfaceY": 17.999999999998003
 }
}