{
 "result": {
  "interfaceWidth": 545,
  "views": {
   "1": {
    "function": "Null",
    "cY": 0.49017199017199753,
    "cX": 0.34495412844035783,
    "mid_view": {},
    "cWidth": 0.6899082568807157,
    "hierarchy": "1",
    "viewType": [
     {
      "layout": "Free",
      "Type": "Tree and Network (Graph)",
      "probability": "1"
     }
    ],
    "cHeight": 0.9803439803439951
   },
   "2": {
    "function": "Null",
    "cY": 0.169533169533,
    "cX": 0.8366972477062157,
    "mid_view": {},
    "cWidth": 0.293577981651,
    "hierarchy": "2",
    "viewType": [
     {
      "layout": "Free",
      "Type": "Panel",
      "probability": "1"
     }
    ],
    "cHeight": 0.339066339066
   },
   "3": {
    "function": "Null",
    "cY": 0.6597051597049975,
    "cX": 0.8366972477062157,
    "mid_view": {},
    "cWidth": 0.293577981651,
    "hierarchy": "3",
    "viewType": [
     {
      "layout": "Free",
      "Type": "Table",
      "probability": "1"
     }
    ],
    "cHeight": 0.641277641277995
   }
  },
  "interfaceHeight": 407,
  "imageHeight": 422,
  "imageWidth": 550,
  "tile": 4,
  "interfaceX": 12.000000000112484,
  "interfaceY": 22.000000000069
 }
}