{
 "result": {
  "tile": 126,
  "imageWidth": 736.25,
  "imageHeight": 450,
  "interfaceWidth": 720,
  "interfaceHeight": 392,
  "views": {
   "1": {
    "hierarchy": "1",
    "cX": 0.07708333333338892,
    "cY": 0.48979591836745917,
    "cWidth": "0.15416666666677784",
    "cHeight": "0.9795918367349183",
    "viewType": [
     {
      "layout": "Free",
      "Type": "Panel",
      "probability": "1"
     }
    ],
    "mid_view": {}
   },
   "2": {
    "hierarchy": "2",
    "cX": 0.4631944444446945,
    "cY": 0.2512755102041633,
    "cWidth": "0.6180555555558334",
    "cHeight": "0.5025510204083266",
    "viewType": [
     {
      "layout": "Free",
      "Type": "Line",
      "probability": "1"
     }
    ],
    "mid_view": {}
   },
   "3": {
    "hierarchy": "3",
    "cX": 0.30555555555580555,
    "cY": 0.7410714285716224,
    "cWidth": "0.30277777777805553",
    "cHeight": "0.4770408163265919",
    "viewType": [
     {
      "layout": "Free",
      "Type": "Point",
      "probability": "1"
     }
    ],
    "mid_view": {}
   },
   "4": {
    "hierarchy": "4",
    "cX": 0.5354166666668333,
    "cY": 0.6262755102043266,
    "cWidth": "0.156944444444",
    "cHeight": "0.247448979592",
    "viewType": [
     {
      "layout": "Free",
      "Type": "Point",
      "probability": "1"
     }
    ],
    "mid_view": {}
   },
   "5": {
    "hierarchy": "5",
    "cX": 0.6930555555557222,
    "cY": 0.6262755102043266,
    "cWidth": "0.15833333333377778",
    "cHeight": "0.247448979592",
    "viewType": [
     {
      "layout": "Free",
      "Type": "Bar",
      "probability": "1"
     }
    ],
    "mid_view": {}
   },
   "6": {
    "hierarchy": "6",
    "cX": 0.6145833333337222,
    "cY": 0.8647959183676225,
    "cWidth": "0.31527777777777777",
    "cHeight": "0.22959183673459185",
    "viewType": [
     {
      "layout": "Free",
      "Type": "Line",
      "probability": "1"
     }
    ],
    "mid_view": {}
   },
   "7": {
    "hierarchy": "7",
    "cX": 0.8805555555558889,
    "cY": 0.11989795918391838,
    "cWidth": "0.21666666666655554",
    "cHeight": "0.23979591836783673",
    "viewType": [
     {
      "layout": "Free",
      "Type": "small multiple",
      "probability": "4"
     }
    ],
    "mid_view": {
     "1": {
      "hierarchy": "7.1",
      "cX": 0.8107638888891667,
      "cY": 0.067602040816449,
      "cWidth": "0.07708333333311101",
      "cHeight": "0.135204081632898",
      "viewType": [
       {
        "Type": "Bar",
        "probability": "1"
       }
      ]
     },
     "2": {
      "hierarchy": "7.2",
      "cX": 0.8833333333335001,
      "cY": 0.067602040816449,
      "cWidth": "0.06805555555555556",
      "cHeight": "0.135204081632898",
      "viewType": [
       {
        "Type": "Bar",
        "probability": "1"
       }
      ]
     },
     "3": {
      "hierarchy": "7.3",
      "cX": 0.9531250000002222,
      "cY": 0.067602040816449,
      "cWidth": "0.07152777777788899",
      "cHeight": "0.135204081632898",
      "viewType": [
       {
        "Type": "Bar",
        "probability": "1"
       }
      ]
     },
     "4": {
      "hierarchy": "7.4",
      "cX": 0.8805555555558889,
      "cY": 0.18750000000036737,
      "cWidth": "0.21666666666655554",
      "cHeight": "0.10459183673493874",
      "viewType": [
       {
        "Type": "Bar",
        "probability": "1"
       }
      ]
     }
    }
   },
   "8": {
    "hierarchy": "8",
    "cX": 0.8805555555558889,
    "cY": 0.6096938775513774,
    "cWidth": "0.21666666666655554",
    "cHeight": "0.7397959183670816",
    "viewType": [
     {
      "layout": "Free",
      "Type": "small multiple",
      "probability": "18"
     }
    ],
    "mid_view": {
     "1": {
      "hierarchy": "8.1",
      "cX": 0.8121527777780556,
      "cY": 0.31377551020444894,
      "cWidth": "0.0798611111108889",
      "cHeight": "0.1479591836732247",
      "viewType": [
       {
        "Type": "Line",
        "probability": "1"
       }
      ]
     },
     "2": {
      "hierarchy": "8.2",
      "cX": 0.8868055555557223,
      "cY": 0.31377551020444894,
      "cWidth": "0.06944444444444449",
      "cHeight": "0.1479591836732247",
      "viewType": [
       {
        "Type": "Line",
        "probability": "1"
       }
      ]
     },
     "3": {
      "hierarchy": "8.3",
      "cX": 0.9552083333335556,
      "cY": 0.31377551020444894,
      "cWidth": "0.06736111111122234",
      "cHeight": "0.1479591836732247",
      "viewType": [
       {
        "Type": "Line",
        "probability": "1"
       }
      ]
     },
     "4": {
      "hierarchy": "8.4",
      "cX": 0.8104166666669445,
      "cY": 0.44897959183697966,
      "cWidth": "0.07638888888866657",
      "cHeight": "0.1224489795918367",
      "viewType": [
       {
        "Type": "Line",
        "probability": "1"
       }
      ]
     },
     "5": {
      "hierarchy": "8.5",
      "cX": 0.8840277777779444,
      "cY": 0.44897959183697966,
      "cWidth": "0.07083333333333336",
      "cHeight": "0.1224489795918367",
      "viewType": [
       {
        "Type": "Line",
        "probability": "1"
       }
      ]
     },
     "6": {
      "hierarchy": "8.6",
      "cX": 0.954166666666889,
      "cY": 0.44897959183697966,
      "cWidth": "0.06944444444455555",
      "cHeight": "0.1224489795918367",
      "viewType": [
       {
        "Type": "Line",
        "probability": "1"
       }
      ]
     },
     "7": {
      "hierarchy": "8.7",
      "cX": 0.8090277777780556,
      "cY": 0.5663265306124898,
      "cWidth": "0.0736111111108888",
      "cHeight": "0.11224489795918369",
      "viewType": [
       {
        "Type": "Line",
        "probability": "1"
       }
      ]
     },
     "8": {
      "hierarchy": "8.8",
      "cX": 0.8826388888890555,
      "cY": 0.5663265306124898,
      "cWidth": "0.07361111111111114",
      "cHeight": "0.11224489795918369",
      "viewType": [
       {
        "Type": "Line",
        "probability": "1"
       }
      ]
     },
     "9": {
      "hierarchy": "8.9",
      "cX": 0.954166666666889,
      "cY": 0.5663265306124898,
      "cWidth": "0.06944444444455555",
      "cHeight": "0.11224489795918369",
      "viewType": [
       {
        "Type": "Line",
        "probability": "1"
       }
      ]
     },
     "10": {
      "hierarchy": "8.10",
      "cX": 0.8100694444447222,
      "cY": 0.6811224489798368,
      "cWidth": "0.07569444444422213",
      "cHeight": "0.11734693877551017",
      "viewType": [
       {
        "Type": "Line",
        "probability": "1"
       }
      ]
     },
     "11": {
      "hierarchy": "8.11",
      "cX": 0.8833333333335001,
      "cY": 0.6811224489798368,
      "cWidth": "0.07083333333333333",
      "cHeight": "0.11734693877551017",
      "viewType": [
       {
        "Type": "Line",
        "probability": "1"
       }
      ]
     },
     "12": {
      "hierarchy": "8.12",
      "cX": 0.9538194444446667,
      "cY": 0.6811224489798368,
      "cWidth": "0.0701388888890001",
      "cHeight": "0.11734693877551017",
      "viewType": [
       {
        "Type": "Line",
        "probability": "1"
       }
      ]
     },
     "13": {
      "hierarchy": "8.13",
      "cX": 0.8097222222225,
      "cY": 0.7984693877553469,
      "cWidth": "0.07499999999977769",
      "cHeight": "0.11734693877551022",
      "viewType": [
       {
        "Type": "Line",
        "probability": "1"
       }
      ]
     },
     "14": {
      "hierarchy": "8.14",
      "cX": 0.8833333333335,
      "cY": 0.7984693877553469,
      "cWidth": "0.07222222222222224",
      "cHeight": "0.11734693877551022",
      "viewType": [
       {
        "Type": "Line",
        "probability": "1"
       }
      ]
     },
     "15": {
      "hierarchy": "8.15",
      "cX": 0.954166666666889,
      "cY": 0.7984693877553469,
      "cWidth": "0.06944444444455555",
      "cHeight": "0.11734693877551022",
      "viewType": [
       {
        "Type": "Line",
        "probability": "1"
       }
      ]
     },
     "16": {
      "hierarchy": "8.16",
      "cX": 0.8097222222225,
      "cY": 0.91836734693901,
      "cWidth": "0.07499999999977769",
      "cHeight": "0.12244897959181611",
      "viewType": [
       {
        "Type": "Line",
        "probability": "1"
       }
      ]
     },
     "17": {
      "hierarchy": "8.17",
      "cX": 0.8847222222223888,
      "cY": 0.91836734693901,
      "cWidth": "0.07500000000000002",
      "cHeight": "0.12244897959181611",
      "viewType": [
       {
        "Type": "Line",
        "probability": "1"
       }
      ]
     },
     "18": {
      "hierarchy": "8.18",
      "cX": 0.9555555555557779,
      "cY": 0.91836734693901,
      "cWidth": "0.06666666666677779",
      "cHeight": "0.12244897959181611",
      "viewType": [
       {
        "Type": "Line",
        "probability": "1"
       }
      ]
     }
    }
   }
  },
  "interfaceX": 3.9999999998800018,
  "interfaceY": 31.999999999903984
 }
}